isolyzer/__init__.py
isolyzer/__init__.pyc
isolyzer/__main__.py
isolyzer/apple.py
isolyzer/apple.pyc
isolyzer/byteconv.py
isolyzer/byteconv.pyc
isolyzer/hsf.py
isolyzer/iso9660.py
isolyzer/iso9660.pyc
isolyzer/isolyzer.py
isolyzer/isolyzer.pyc
isolyzer/shared.py
isolyzer/shared.pyc
isolyzer/udf.py
isolyzer/udf.pyc
tests/__init__.py
tests/unit/__init__.py
tests/unit/rest_todo.py
tests/unit/test_isolyzer.py
tests/unit/test_testfiles.py
isolyzer-1.4.0.dist-info/LICENSE.txt
isolyzer-1.4.0.dist-info/METADATA
isolyzer-1.4.0.dist-info/WHEEL
isolyzer-1.4.0.dist-info/entry_points.txt
isolyzer-1.4.0.dist-info/top_level.txt
isolyzer-1.4.0.dist-info/RECORD
