Metadata-Version: 2.1
Name: isolyzer
Version: 1.4.0
Summary: Verify size of ISO image
Home-page: https://github.com/KBNLresearch/isolyzer
Author: Johan van der Knijff
Author-email: johan.vanderknijff@kb.nl
Maintainer: Johan van der Knijff
Maintainer-email: johan.vanderknijff@kb.nl
License: Apache License 2.0
Download-URL: https://github.com/KBNLresearch/isolyzer/archive/1.4.0.tar.gz
Platform: POSIX
Platform: Windows
Classifier: Environment :: Console
Classifier: Programming Language :: Python :: 3
Requires-Python: >=3.2, <4
Requires-Dist: setuptools
